pyftpclient/__init__.py
pyftpclient/client_base.py
pyftpclient/ftp_client.py
pyftpclient/sftp_client.py
pyftpclient/shortcurts.py
pyftpclient-0.2.0.dist-info/METADATA
pyftpclient-0.2.0.dist-info/WHEEL
pyftpclient-0.2.0.dist-info/licenses/LICENCE
pyftpclient-0.2.0.dist-info/RECORD
