Metadata-Version: 2.4
Name: pyftpclient
Version: 0.2.0
Summary: ftp client wrapper to simplify working with paramiko or ftplib
Project-URL: Homepage, https://github.com/ahcub/pyftpclient
Project-URL: Repository, https://github.com/ahcub/pyftpclient
Author-email: Alex Buchkovsky <alex.buchkovsky@gmail.com>
License: Copyright (c) 2018, Alexander Buchkovsky
License-File: LICENCE
Keywords: client,ftp,sftp,wrapper
Classifier: License :: OSI Approved :: BSD License
Classifier: Operating System :: OS Independent
Classifier: Programming Language :: Python :: 3
Classifier: Programming Language :: Python :: 3.14
Requires-Python: >=3.14
Requires-Dist: os-utils==0.2.0
Requires-Dist: paramiko==4.0.0
Provides-Extra: dev
Requires-Dist: mypy==1.18.2; extra == 'dev'
Requires-Dist: pytest-cov==7.0.0; extra == 'dev'
Requires-Dist: pytest-mock==3.15.1; extra == 'dev'
Requires-Dist: pytest==9.0.0; extra == 'dev'
Requires-Dist: ruff==0.14.4; extra == 'dev'
Requires-Dist: types-paramiko==4.0.0.20250822; extra == 'dev'
